obj2mjcf/__init__.py
obj2mjcf/cli.py
obj2mjcf/constants.py
obj2mjcf/material.py
obj2mjcf/mjcf_builder.py
obj2mjcf/py.typed
obj2mjcf-0.0.25.dist-info/LICENSE
obj2mjcf-0.0.25.dist-info/METADATA
obj2mjcf-0.0.25.dist-info/WHEEL
obj2mjcf-0.0.25.dist-info/entry_points.txt
obj2mjcf-0.0.25.dist-info/top_level.txt
obj2mjcf-0.0.25.dist-info/RECORD
