Metadata-Version: 2.1
Name: obj2mjcf
Version: 0.0.25
Summary: A CLI for processing composite Wavefront OBJ files for use in MuJoCo
Home-page: https://github.com/kevinzakka/obj2mjcf
Author: Kevin Zakka
Author-email: kevinarmandzakka@gmail.com
Maintainer: Kevin Zakka
Maintainer-email: kevinarmandzakka@gmail.com
License: MIT
Classifier: Development Status :: 3 - Alpha
Classifier: Intended Audience :: Developers
Classifier: Intended Audience :: Science/Research
Classifier: License :: OSI Approved :: MIT License
Classifier: Natural Language :: English
Classifier: Programming Language :: Python :: 3
Classifier: Programming Language :: Python :: 3.8
Classifier: Programming Language :: Python :: 3.9
Classifier: Programming Language :: Python :: 3.10
Classifier: Programming Language :: Python :: 3.11
Classifier: Programming Language :: Python :: 3.12
Classifier: Topic :: Scientific/Engineering :: Artificial Intelligence
Requires-Python: >=3.8
License-File: LICENSE
Requires-Dist: trimesh >=3.15.5
Requires-Dist: Pillow >=9.2.0
Requires-Dist: mujoco >=2.2.0
Requires-Dist: tyro >=0.3.22
Requires-Dist: numpy
Requires-Dist: termcolor >=2.0.1
Requires-Dist: lxml >=4.9.1
Requires-Dist: coacd >=1.0.0
Provides-Extra: dev
Requires-Dist: black ; extra == 'dev'
Requires-Dist: mypy ; extra == 'dev'
Requires-Dist: ruff ; extra == 'dev'
Requires-Dist: pytest ; extra == 'dev'
Requires-Dist: trimesh >=3.15.5 ; extra == 'dev'
Requires-Dist: Pillow >=9.2.0 ; extra == 'dev'
Requires-Dist: mujoco >=2.2.0 ; extra == 'dev'
Requires-Dist: tyro >=0.3.22 ; extra == 'dev'
Requires-Dist: numpy ; extra == 'dev'
Requires-Dist: termcolor >=2.0.1 ; extra == 'dev'
Requires-Dist: lxml >=4.9.1 ; extra == 'dev'
Requires-Dist: coacd >=1.0.0 ; extra == 'dev'
Provides-Extra: test
Requires-Dist: pytest ; extra == 'test'
Requires-Dist: trimesh >=3.15.5 ; extra == 'test'
Requires-Dist: Pillow >=9.2.0 ; extra == 'test'
Requires-Dist: mujoco >=2.2.0 ; extra == 'test'
Requires-Dist: tyro >=0.3.22 ; extra == 'test'
Requires-Dist: numpy ; extra == 'test'
Requires-Dist: termcolor >=2.0.1 ; extra == 'test'
Requires-Dist: lxml >=4.9.1 ; extra == 'test'
Requires-Dist: coacd >=1.0.0 ; extra == 'test'
Provides-Extra: testing
Requires-Dist: pytest ; extra == 'testing'
Requires-Dist: trimesh >=3.15.5 ; extra == 'testing'
Requires-Dist: Pillow >=9.2.0 ; extra == 'testing'
Requires-Dist: mujoco >=2.2.0 ; extra == 'testing'
Requires-Dist: tyro >=0.3.22 ; extra == 'testing'
Requires-Dist: numpy ; extra == 'testing'
Requires-Dist: termcolor >=2.0.1 ; extra == 'testing'
Requires-Dist: lxml >=4.9.1 ; extra == 'testing'
Requires-Dist: coacd >=1.0.0 ; extra == 'testing'
